{
    "CurrentInfo": {
      "CurrentMatch": "",
      "RedName": "",
      "BlueName": "",
      "RoundTime": 120,
      "RestTime": 60,
      "CurrentRoundTime": 120,
      "CurrentRestTime": 60,
      "PTGscore": 12,
      "PUNnumber": 5,
      "CurrentRound": 1,
      "IsFinished": false,
      "IsStarted": false,
      "IsTimeOut": false,
      "RedGamJeom": 0,
      "BlueGamJeom": 0,
      "RedScore": {
        "1pts": 0,
        "2pts": 0,
        "3pts": 0,
        "4pts": 0,
        "5pts": 0
      },
      "BlueScore": {
        "1pts": 0,
        "2pts": 0,
        "3pts": 0,
        "4pts": 0,
        "5pts": 0
      },
      "Round1": {
        "RoundWinner": "",
        "RoundWinningReason": ""
      },
      "Round2": {
        "RoundWinner": "",
        "RoundWinningReason": ""
      },
      "Round3": {
        "RoundWinner": "",
        "RoundWinningReason": ""
      }
    },
    "MatchResults": {
    }
  }